<annotation><filename>000108</filename><folder>hard_negatives</folder><object><name>non_ship</name><pose>Unspecified</pose><truncated>0</truncated><difficult>0</difficult><bndbox><xmin>34</xmin><ymin>89</ymin><xmax>39</xmax><ymax>95</ymax></bndbox></object><object><name>non_ship</name><pose>Unspecified</pose><truncated>0</truncated><difficult>0</difficult><bndbox><xmin>49</xmin><ymin>110</ymin><xmax>54</xmax><ymax>115</ymax></bndbox></object><object><name>non_ship</name><pose>Unspecified</pose><truncated>0</truncated><difficult>0</difficult><bndbox><xmin>71</xmin><ymin>136</ymin><xmax>76</xmax><ymax>141</ymax></bndbox></object></annotation>